{
  "features": [
    {
      "name": "hello",
      "inNetworks": [
        {
          "network": "my first graph",
          "neighbors": [
            "aloha",
            "gutentag"
          ]
        }
      ]
    },
    {
      "name": "aloha",
      "inNetworks": [
        {
          "network": "my first graph",
          "neighbors": [
            "hello"
          ]
        }
      ]
    },
    {
      "name": "gutentag",
      "inNetworks": [
        {
          "network": "my first graph",
          "neighbors": [
            "hello",
            "hola",
            "buenos dias",
            "bien venidos"
          ]
        }
      ]
    },
    {
      "name": "buenos dias",
      "inNetworks": [
        {
          "network": "my first graph",
          "neighbors": [
            "gutentag"
          ]
        }
      ]
    },
    {
      "name": "hola",
      "inNetworks": [
        {
          "network": "my first graph",
          "neighbors": [
            "gutentag"
          ]
        }
      ]
    },
    {
      "name": "bien venidos",
      "inNetworks": [
        {
          "network": "my first graph",
          "neighbors": [
            "gutentag"
          ]
        }
      ]
    }
  ],
  "networks": [
    {
      "name": "my first graph",
      "graph": {
        "options": {
          "type": "directed",
          "multi": false,
          "allowSelfLoops": true
        },
        "attributes": {},
        "nodes": [
          {
            "key": "hello"
          },
          {
            "key": "aloha"
          },
          {
            "key": "gutentag"
          },
          {
            "key": "buenos dias"
          },
          {
            "key": "hola"
          },
          {
            "key": "bien venidos"
          }
        ],
        "edges": [
          {
            "key": "geid_201_0",
            "source": "hello",
            "target": "aloha"
          },
          {
            "key": "geid_201_1",
            "source": "hello",
            "target": "gutentag"
          },
          {
            "key": "geid_201_2",
            "source": "gutentag",
            "target": "buenos dias"
          },
          {
            "key": "geid_201_3",
            "source": "hola",
            "target": "gutentag"
          },
          {
            "key": "geid_201_4",
            "source": "gutentag",
            "target": "bien venidos"
          }
        ]
      }
    }
  ]
}